encrypter.py
encrypter/encrypter.py
src/encrypter.py
encrypter-0.1.dist-info/LICENSE
encrypter-0.1.dist-info/METADATA
encrypter-0.1.dist-info/WHEEL
encrypter-0.1.dist-info/top_level.txt
encrypter-0.1.dist-info/RECORD
